fcal/__init__.py
fcal/main.py
fcal-0.8.1.dist-info/METADATA
fcal-0.8.1.dist-info/WHEEL
fcal-0.8.1.dist-info/entry_points.txt
fcal-0.8.1.dist-info/RECORD
